graphRLnx/__init__.py
graphRLnx/envs/__init__.py
graphRLnx/envs/graphRLnx.py
graphRLnx/envs/test.py
graphRLnx-0.0.3.dist-info/LICENSE
graphRLnx-0.0.3.dist-info/METADATA
graphRLnx-0.0.3.dist-info/WHEEL
graphRLnx-0.0.3.dist-info/top_level.txt
graphRLnx-0.0.3.dist-info/RECORD
