Metadata-Version: 2.1
Name: graphRLnx
Version: 0.0.3
Summary: a directed acyclic graph environment for use with openAI gym, with a networkX backend
Home-page: https://github.com/luludarcy/graphRLnx
Author: Laura D'Arcy
Author-email: luludarcy@gmail.com
License: UNKNOWN
Platform: UNKNOWN
Classifier: Programming Language :: Python :: 3
Classifier: License :: OSI Approved :: MIT License
Classifier: Operating System :: OS Independent
Requires-Dist: gym
Requires-Dist: networkx
